pupygrib/__init__.py
pupygrib/base.py
pupygrib/binary.py
pupygrib/edition2.py
pupygrib/exceptions.py
pupygrib/fields.py
pupygrib/py.typed
pupygrib/utils.py
pupygrib/edition1/__init__.py
pupygrib/edition1/bds.py
pupygrib/edition1/bitmap.py
pupygrib/edition1/fields.py
pupygrib/edition1/gds.py
pupygrib/edition1/pds.py
pupygrib-0.9.0.dist-info/LICENSE.txt
pupygrib-0.9.0.dist-info/METADATA
pupygrib-0.9.0.dist-info/WHEEL
pupygrib-0.9.0.dist-info/top_level.txt
pupygrib-0.9.0.dist-info/RECORD
