Metadata-Version: 2.1
Name: pupygrib
Version: 0.9.0
Summary: A light-weight pure Python GRIB reader
Home-page: https://gitlab.com/gorilladev/pupygrib
Author: Mattias Jakobsson
Author-email: mjakob422@gmail.com
License: UNKNOWN
Project-URL: Bug Tracker, https://gitlab.com/gorilladev/pupygrib/-/issues
Keywords: grib,grid,data,meteorology
Platform: UNKNOWN
Classifier: Development Status :: 3 - Alpha
Classifier: Intended Audience :: Developers
Classifier: Topic :: Scientific/Engineering :: Atmospheric Science
Classifier: License :: OSI Approved :: GNU General Public License v3 (GPLv3)
Classifier: Programming Language :: Python :: 3
Classifier: Typing :: Typed
Requires-Python: >=3.7
License-File: LICENSE.txt
Requires-Dist: numpy
